{"commandline":"C:\\Users\\minhl\\AppData\\Local\\Temp\\go-build1754508248\\b001\\exe\\recon.exe google.com","time":"2024-09-13T01:04:21+07:00","results":[{"input":{"FFUFHASH":"07f07e","FUZZ":".git/logs/"},"position":14,"status":200,"length":22904,"words":587,"lines":19,"content-type":"text/html; charset=ISO-8859-1","redirectlocation":"","scraper":{},"duration":140541000,"resultfile":"","url":"https://google.com","host":".git/logs/.google.com"},{"input":{"FFUFHASH":"07f07d","FUZZ":".git/index"},"position":13,"status":200,"length":22814,"words":587,"lines":19,"content-type":"text/html; charset=ISO-8859-1","redirectlocation":"","scraper":{},"duration":121049300,"resultfile":"","url":"https://google.com","host":".git/index.google.com"},{"input":{"FFUFHASH":"07f07b","FUZZ":".git/HEAD"},"position":11,"status":200,"length":22770,"words":587,"lines":19,"content-type":"text/html; charset=ISO-8859-1","redirectlocation":"","scraper":{},"duration":129970100,"resultfile":"","url":"https://google.com","host":".git/HEAD.google.com"},{"input":{"FFUFHASH":"07f07c","FUZZ":".git/config"},"position":12,"status":200,"length":22818,"words":587,"lines":19,"content-type":"text/html; charset=ISO-8859-1","redirectlocation":"","scraper":{},"duration":108299800,"resultfile":"","url":"https://google.com","host":".git/config.google.com"},{"input":{"FFUFHASH":"07f072a","FUZZ":".well-known/acme-challenge"},"position":42,"status":200,"length":22818,"words":587,"lines":19,"content-type":"text/html; charset=ISO-8859-1","redirectlocation":"","scraper":{},"duration":59041800,"resultfile":"","url":"https://google.com","host":".well-known/acme-challenge.google.com"},{"input":{"FFUFHASH":"07f072b","FUZZ":".well-known/apple-app-site-association"},"position":43,"status":200,"length":22831,"words":587,"lines":19,"content-type":"text/html; charset=ISO-8859-1","redirectlocation":"","scraper":{},"duration":66538900,"resultfile":"","url":"https://google.com","host":".well-known/apple-app-site-association.google.com"},{"input":{"FFUFHASH":"07f072c","FUZZ":".well-known/apple-developer-merchantid-domain-association"},"position":44,"status":200,"length":22872,"words":587,"lines":19,"content-type":"text/html; charset=ISO-8859-1","redirectlocation":"","scraper":{},"duration":71772800,"resultfile":"","url":"https://google.com","host":".well-known/apple-developer-merchantid-domain-association.google.com"},{"input":{"FFUFHASH":"07f0726","FUZZ":".svn/entries"},"position":38,"status":200,"length":22780,"words":587,"lines":19,"content-type":"text/html; charset=ISO-8859-1","redirectlocation":"","scraper":{},"duration":84218200,"resultfile":"","url":"https://google.com","host":".svn/entries.google.com"},{"input":{"FFUFHASH":"07f072e","FUZZ":".well-known/assetlinks.json"},"position":46,"status":200,"length":22851,"words":587,"lines":19,"content-type":"text/html; charset=ISO-8859-1","redirectlocation":"","scraper":{},"duration":68753000,"resultfile":"","url":"https://google.com","host":".well-known/assetlinks.json.google.com"},{"input":{"FFUFHASH":"07f072d","FUZZ":".well-known/ashrae"},"position":45,"status":200,"length":22917,"words":587,"lines":19,"content-type":"text/html; charset=ISO-8859-1","redirectlocation":"","scraper":{},"duration":78425700,"resultfile":"","url":"https://google.com","host":".well-known/ashrae.google.com"},{"input":{"FFUFHASH":"07f072f","FUZZ":".well-known/autoconfig/mail"},"position":47,"status":200,"length":22861,"words":587,"lines":19,"content-type":"text/html; charset=ISO-8859-1","redirectlocation":"","scraper":{},"duration":74740100,"resultfile":"","url":"https://google.com","host":".well-known/autoconfig/mail.google.com"},{"input":{"FFUFHASH":"07f0731","FUZZ":".well-known/caldav"},"position":49,"status":200,"length":22847,"words":587,"lines":19,"content-type":"text/html; charset=ISO-8859-1","redirectlocation":"","scraper":{},"duration":72566600,"resultfile":"","url":"https://google.com","host":".well-known/caldav.google.com"},{"input":{"FFUFHASH":"07f0730","FUZZ":".well-known/browserid"},"position":48,"status":200,"length":22885,"words":587,"lines":19,"content-type":"text/html; charset=ISO-8859-1","redirectlocation":"","scraper":{},"duration":75798700,"resultfile":"","url":"https://google.com","host":".well-known/browserid.google.com"},{"input":{"FFUFHASH":"07f0732","FUZZ":".well-known/carddav"},"position":50,"status":200,"length":22889,"words":587,"lines":19,"content-type":"text/html; charset=ISO-8859-1","redirectlocation":"","scraper":{},"duration":71497300,"resultfile":"","url":"https://google.com","host":".well-known/carddav.google.com"},{"input":{"FFUFHASH":"07f0734","FUZZ":".well-known/coap"},"position":52,"status":200,"length":22887,"words":587,"lines":19,"content-type":"text/html; charset=ISO-8859-1","redirectlocation":"","scraper":{},"duration":68005200,"resultfile":"","url":"https://google.com","host":".well-known/coap.google.com"},{"input":{"FFUFHASH":"07f0733","FUZZ":".well-known/change-password"},"position":51,"status":200,"length":22878,"words":587,"lines":19,"content-type":"text/html; charset=ISO-8859-1","redirectlocation":"","scraper":{},"duration":79559500,"resultfile":"","url":"https://google.com","host":".well-known/change-password.google.com"},{"input":{"FFUFHASH":"07f0736","FUZZ":".well-known/csvm"},"position":54,"status":200,"length":22897,"words":587,"lines":19,"content-type":"text/html; charset=ISO-8859-1","redirectlocation":"","scraper":{},"duration":73139700,"resultfile":"","url":"https://google.com","host":".well-known/csvm.google.com"},{"input":{"FFUFHASH":"07f0735","FUZZ":".well-known/core"},"position":53,"status":200,"length":22857,"words":587,"lines":19,"content-type":"text/html; charset=ISO-8859-1","redirectlocation":"","scraper":{},"duration":74118500,"resultfile":"","url":"https://google.com","host":".well-known/core.google.com"},{"input":{"FFUFHASH":"07f0737","FUZZ":".well-known/dnt"},"position":55,"status":200,"length":22928,"words":587,"lines":19,"content-type":"text/html; charset=ISO-8859-1","redirectlocation":"","scraper":{},"duration":61292800,"resultfile":"","url":"https://google.com","host":".well-known/dnt.google.com"},{"input":{"FFUFHASH":"07f0738","FUZZ":".well-known/dnt-policy.txt"},"position":56,"status":200,"length":22797,"words":587,"lines":19,"content-type":"text/html; charset=ISO-8859-1","redirectlocation":"","scraper":{},"duration":69415200,"resultfile":"","url":"https://google.com","host":".well-known/dnt-policy.txt.google.com"},{"input":{"FFUFHASH":"07f073e","FUZZ":".well-known/hoba"},"position":62,"status":200,"length":22791,"words":587,"lines":19,"content-type":"text/html; charset=ISO-8859-1","redirectlocation":"","scraper":{},"duration":64522100,"resultfile":"","url":"https://google.com","host":".well-known/hoba.google.com"},{"input":{"FFUFHASH":"07f073a","FUZZ":".well-known/ecips"},"position":58,"status":200,"length":22964,"words":587,"lines":19,"content-type":"text/html; charset=ISO-8859-1","redirectlocation":"","scraper":{},"duration":65981500,"resultfile":"","url":"https://google.com","host":".well-known/ecips.google.com"},{"input":{"FFUFHASH":"07f073d","FUZZ":".well-known/genid"},"position":61,"status":200,"length":22776,"words":587,"lines":19,"content-type":"text/html; charset=ISO-8859-1","redirectlocation":"","scraper":{},"duration":73148000,"resultfile":"","url":"https://google.com","host":".well-known/genid.google.com"},{"input":{"FFUFHASH":"07f073b","FUZZ":".well-known/enterprise-transport-security"},"position":59,"status":200,"length":22765,"words":587,"lines":19,"content-type":"text/html; charset=ISO-8859-1","redirectlocation":"","scraper":{},"duration":77707100,"resultfile":"","url":"https://google.com","host":".well-known/enterprise-transport-security.google.com"},{"input":{"FFUFHASH":"07f0739","FUZZ":".well-known/dots"},"position":57,"status":200,"length":22885,"words":587,"lines":19,"content-type":"text/html; charset=ISO-8859-1","redirectlocation":"","scraper":{},"duration":84614600,"resultfile":"","url":"https://google.com","host":".well-known/dots.google.com"},{"input":{"FFUFHASH":"07f073c","FUZZ":".well-known/est"},"position":60,"status":200,"length":22914,"words":587,"lines":19,"content-type":"text/html; charset=ISO-8859-1","redirectlocation":"","scraper":{},"duration":82174400,"resultfile":"","url":"https://google.com","host":".well-known/est.google.com"},{"input":{"FFUFHASH":"07f0740","FUZZ":".well-known/host-meta.json"},"position":64,"status":200,"length":22738,"words":587,"lines":19,"content-type":"text/html; charset=ISO-8859-1","redirectlocation":"","scraper":{},"duration":76417700,"resultfile":"","url":"https://google.com","host":".well-known/host-meta.json.google.com"},{"input":{"FFUFHASH":"07f0743","FUZZ":".well-known/jmap"},"position":67,"status":200,"length":22893,"words":587,"lines":19,"content-type":"text/html; charset=ISO-8859-1","redirectlocation":"","scraper":{},"duration":72770000,"resultfile":"","url":"https://google.com","host":".well-known/jmap.google.com"},{"input":{"FFUFHASH":"07f0745","FUZZ":".well-known/keybase.txt"},"position":69,"status":200,"length":22860,"words":587,"lines":19,"content-type":"text/html; charset=ISO-8859-1","redirectlocation":"","scraper":{},"duration":74807900,"resultfile":"","url":"https://google.com","host":".well-known/keybase.txt.google.com"},{"input":{"FFUFHASH":"07f073f","FUZZ":".well-known/host-meta"},"position":63,"status":200,"length":22864,"words":587,"lines":19,"content-type":"text/html; charset=ISO-8859-1","redirectlocation":"","scraper":{},"duration":86556600,"resultfile":"","url":"https://google.com","host":".well-known/host-meta.google.com"},{"input":{"FFUFHASH":"07f0744","FUZZ":".well-known/jwks.json"},"position":68,"status":200,"length":22858,"words":587,"lines":19,"content-type":"text/html; charset=ISO-8859-1","redirectlocation":"","scraper":{},"duration":75849300,"resultfile":"","url":"https://google.com","host":".well-known/jwks.json.google.com"},{"input":{"FFUFHASH":"07f0742","FUZZ":".well-known/idp-proxy"},"position":66,"status":200,"length":22863,"words":587,"lines":19,"content-type":"text/html; charset=ISO-8859-1","redirectlocation":"","scraper":{},"duration":84269600,"resultfile":"","url":"https://google.com","host":".well-known/idp-proxy.google.com"},{"input":{"FFUFHASH":"07f0750","FUZZ":".well-known/openid-federation"},"position":80,"status":200,"length":22812,"words":587,"lines":19,"content-type":"text/html; charset=ISO-8859-1","redirectlocation":"","scraper":{},"duration":64031800,"resultfile":"","url":"https://google.com","host":".well-known/openid-federation.google.com"},{"input":{"FFUFHASH":"07f0747","FUZZ":".well-known/matrix"},"position":71,"status":200,"length":22922,"words":587,"lines":19,"content-type":"text/html; charset=ISO-8859-1","redirectlocation":"","scraper":{},"duration":74171400,"resultfile":"","url":"https://google.com","host":".well-known/matrix.google.com"},{"input":{"FFUFHASH":"07f0749","FUZZ":".well-known/mta-sts.txt"},"position":73,"status":200,"length":22866,"words":587,"lines":19,"content-type":"text/html; charset=ISO-8859-1","redirectlocation":"","scraper":{},"duration":77323100,"resultfile":"","url":"https://google.com","host":".well-known/mta-sts.txt.google.com"},{"input":{"FFUFHASH":"07f0746","FUZZ":".well-known/looking-glass"},"position":70,"status":200,"length":22830,"words":587,"lines":19,"content-type":"text/html; charset=ISO-8859-1","redirectlocation":"","scraper":{},"duration":86091700,"resultfile":"","url":"https://google.com","host":".well-known/looking-glass.google.com"},{"input":{"FFUFHASH":"07f0752","FUZZ":".well-known/openpgpkey"},"position":82,"status":200,"length":22841,"words":587,"lines":19,"content-type":"text/html; charset=ISO-8859-1","redirectlocation":"","scraper":{},"duration":77341600,"resultfile":"","url":"https://google.com","host":".well-known/openpgpkey.google.com"},{"input":{"FFUFHASH":"07f074f","FUZZ":".well-known/openid-configuration"},"position":79,"status":200,"length":22906,"words":587,"lines":19,"content-type":"text/html; charset=ISO-8859-1","redirectlocation":"","scraper":{},"duration":78981000,"resultfile":"","url":"https://google.com","host":".well-known/openid-configuration.google.com"},{"input":{"FFUFHASH":"07f0751","FUZZ":".well-known/openorg"},"position":81,"status":200,"length":22875,"words":587,"lines":19,"content-type":"text/html; charset=ISO-8859-1","redirectlocation":"","scraper":{},"duration":82662500,"resultfile":"","url":"https://google.com","host":".well-known/openorg.google.com"},{"input":{"FFUFHASH":"07f074d","FUZZ":".well-known/nodeinfo"},"position":77,"status":200,"length":22857,"words":587,"lines":19,"content-type":"text/html; charset=ISO-8859-1","redirectlocation":"","scraper":{},"duration":81812100,"resultfile":"","url":"https://google.com","host":".well-known/nodeinfo.google.com"},{"input":{"FFUFHASH":"07f074a","FUZZ":".well-known/mud"},"position":74,"status":200,"length":22920,"words":587,"lines":19,"content-type":"text/html; charset=ISO-8859-1","redirectlocation":"","scraper":{},"duration":86210200,"resultfile":"","url":"https://google.com","host":".well-known/mud.google.com"},{"input":{"FFUFHASH":"07f0748","FUZZ":".well-known/mercure"},"position":72,"status":200,"length":22934,"words":587,"lines":19,"content-type":"text/html; charset=ISO-8859-1","redirectlocation":"","scraper":{},"duration":103358700,"resultfile":"","url":"https://google.com","host":".well-known/mercure.google.com"},{"input":{"FFUFHASH":"07f074c","FUZZ":".well-known/ni"},"position":76,"status":200,"length":22858,"words":587,"lines":19,"content-type":"text/html; charset=ISO-8859-1","redirectlocation":"","scraper":{},"duration":98455400,"resultfile":"","url":"https://google.com","host":".well-known/ni.google.com"},{"input":{"FFUFHASH":"07f074b","FUZZ":".well-known/nfv-oauth-server-configuration"},"position":75,"status":200,"length":22853,"words":587,"lines":19,"content-type":"text/html; charset=ISO-8859-1","redirectlocation":"","scraper":{},"duration":93191400,"resultfile":"","url":"https://google.com","host":".well-known/nfv-oauth-server-configuration.google.com"},{"input":{"FFUFHASH":"07f074e","FUZZ":".well-known/oauth-authorization-server"},"position":78,"status":200,"length":22940,"words":587,"lines":19,"content-type":"text/html; charset=ISO-8859-1","redirectlocation":"","scraper":{},"duration":90316200,"resultfile":"","url":"https://google.com","host":".well-known/oauth-authorization-server.google.com"},{"input":{"FFUFHASH":"07f0759","FUZZ":".well-known/security.txt"},"position":89,"status":200,"length":22824,"words":587,"lines":19,"content-type":"text/html; charset=ISO-8859-1","redirectlocation":"","scraper":{},"duration":82638600,"resultfile":"","url":"https://google.com","host":".well-known/security.txt.google.com"},{"input":{"FFUFHASH":"07f0755","FUZZ":".well-known/pvd"},"position":85,"status":200,"length":22943,"words":587,"lines":19,"content-type":"text/html; charset=ISO-8859-1","redirectlocation":"","scraper":{},"duration":88056800,"resultfile":"","url":"https://google.com","host":".well-known/pvd.google.com"},{"input":{"FFUFHASH":"07f0753","FUZZ":".well-known/pki-validation"},"position":83,"status":200,"length":22854,"words":587,"lines":19,"content-type":"text/html; charset=ISO-8859-1","redirectlocation":"","scraper":{},"duration":87395700,"resultfile":"","url":"https://google.com","host":".well-known/pki-validation.google.com"},{"input":{"FFUFHASH":"07f0756","FUZZ":".well-known/reload-config"},"position":86,"status":200,"length":22834,"words":587,"lines":19,"content-type":"text/html; charset=ISO-8859-1","redirectlocation":"","scraper":{},"duration":91534500,"resultfile":"","url":"https://google.com","host":".well-known/reload-config.google.com"},{"input":{"FFUFHASH":"07f075e","FUZZ":".well-known/timezone"},"position":94,"status":200,"length":22938,"words":587,"lines":19,"content-type":"text/html; charset=ISO-8859-1","redirectlocation":"","scraper":{},"duration":88696900,"resultfile":"","url":"https://google.com","host":".well-known/timezone.google.com"},{"input":{"FFUFHASH":"07f0758","FUZZ":".well-known/resourcesync"},"position":88,"status":200,"length":22940,"words":587,"lines":19,"content-type":"text/html; charset=ISO-8859-1","redirectlocation":"","scraper":{},"duration":92328800,"resultfile":"","url":"https://google.com","host":".well-known/resourcesync.google.com"},{"input":{"FFUFHASH":"07f0757","FUZZ":".well-known/repute-template"},"position":87,"status":200,"length":22922,"words":587,"lines":19,"content-type":"text/html; charset=ISO-8859-1","redirectlocation":"","scraper":{},"duration":95977500,"resultfile":"","url":"https://google.com","host":".well-known/repute-template.google.com"},{"input":{"FFUFHASH":"07f0754","FUZZ":".well-known/posh"},"position":84,"status":200,"length":22854,"words":587,"lines":19,"content-type":"text/html; charset=ISO-8859-1","redirectlocation":"","scraper":{},"duration":100116000,"resultfile":"","url":"https://google.com","host":".well-known/posh.google.com"},{"input":{"FFUFHASH":"07f075f","FUZZ":".well-known/uma2-configuration"},"position":95,"status":200,"length":22858,"words":587,"lines":19,"content-type":"text/html; charset=ISO-8859-1","redirectlocation":"","scraper":{},"duration":86249400,"resultfile":"","url":"https://google.com","host":".well-known/uma2-configuration.google.com"},{"input":{"FFUFHASH":"07f075a","FUZZ":".well-known/humans.txt"},"position":90,"status":200,"length":22802,"words":587,"lines":19,"content-type":"text/html; charset=ISO-8859-1","redirectlocation":"","scraper":{},"duration":98262900,"resultfile":"","url":"https://google.com","host":".well-known/humans.txt.google.com"},{"input":{"FFUFHASH":"07f075c","FUZZ":".well-known/thread"},"position":92,"status":200,"length":22903,"words":587,"lines":19,"content-type":"text/html; charset=ISO-8859-1","redirectlocation":"","scraper":{},"duration":99825900,"resultfile":"","url":"https://google.com","host":".well-known/thread.google.com"},{"input":{"FFUFHASH":"07f075b","FUZZ":".well-known/stun-key"},"position":91,"status":200,"length":22828,"words":587,"lines":19,"content-type":"text/html; charset=ISO-8859-1","redirectlocation":"","scraper":{},"duration":101861300,"resultfile":"","url":"https://google.com","host":".well-known/stun-key.google.com"},{"input":{"FFUFHASH":"07f075d","FUZZ":".well-known/time"},"position":93,"status":200,"length":22835,"words":587,"lines":19,"content-type":"text/html; charset=ISO-8859-1","redirectlocation":"","scraper":{},"duration":100816100,"resultfile":"","url":"https://google.com","host":".well-known/time.google.com"},{"input":{"FFUFHASH":"07f0760","FUZZ":".well-known/void"},"position":96,"status":200,"length":22772,"words":587,"lines":19,"content-type":"text/html; charset=ISO-8859-1","redirectlocation":"","scraper":{},"duration":94338800,"resultfile":"","url":"https://google.com","host":".well-known/void.google.com"},{"input":{"FFUFHASH":"07f0761","FUZZ":".well-known/webfinger"},"position":97,"status":200,"length":22868,"words":587,"lines":19,"content-type":"text/html; charset=ISO-8859-1","redirectlocation":"","scraper":{},"duration":97679700,"resultfile":"","url":"https://google.com","host":".well-known/webfinger.google.com"},{"input":{"FFUFHASH":"07f076d","FUZZ":"1"},"position":109,"status":301,"length":220,"words":9,"lines":7,"content-type":"text/html; charset=UTF-8","redirectlocation":"https://one.google.com/","scraper":{},"duration":65500300,"resultfile":"","url":"https://google.com","host":"1.google.com"},{"input":{"FFUFHASH":"07f0741","FUZZ":".well-known/http-opportunistic"},"position":65,"status":200,"length":22876,"words":587,"lines":19,"content-type":"text/html; charset=ISO-8859-1","redirectlocation":"","scraper":{},"duration":192655100,"resultfile":"","url":"https://google.com","host":".well-known/http-opportunistic.google.com"},{"input":{"FFUFHASH":"07f07c7","FUZZ":"About"},"position":199,"status":301,"length":218,"words":9,"lines":7,"content-type":"text/html; charset=UTF-8","redirectlocation":"https://about.google/","scraper":{},"duration":34242700,"resultfile":"","url":"https://google.com","host":"About.google.com"},{"input":{"FFUFHASH":"07f07c1","FUZZ":"@"},"position":193,"status":200,"length":22843,"words":587,"lines":19,"content-type":"text/html; charset=ISO-8859-1","redirectlocation":"","scraper":{},"duration":68929900,"resultfile":"","url":"https://google.com","host":"@.google.com"},{"input":{"FFUFHASH":"07f07d0","FUZZ":"Archive"},"position":208,"status":302,"length":220,"words":9,"lines":7,"content-type":"text/html; charset=UTF-8","redirectlocation":"https://archive.google/","scraper":{},"duration":45623600,"resultfile":"","url":"https://google.com","host":"Archive.google.com"},{"input":{"FFUFHASH":"07f07d6","FUZZ":"Blog"},"position":214,"status":301,"length":221,"words":9,"lines":7,"content-type":"text/html; charset=UTF-8","redirectlocation":"https://www.blog.google/","scraper":{},"duration":42095300,"resultfile":"","url":"https://google.com","host":"Blog.google.com"},{"input":{"FFUFHASH":"07f07df","FUZZ":"CVS/Repository"},"position":223,"status":200,"length":22868,"words":587,"lines":19,"content-type":"text/html; charset=ISO-8859-1","redirectlocation":"","scraper":{},"duration":61828700,"resultfile":"","url":"https://google.com","host":"CVS/Repository.google.com"},{"input":{"FFUFHASH":"07f07de","FUZZ":"CVS/Entries"},"position":222,"status":200,"length":22889,"words":587,"lines":19,"content-type":"text/html; charset=ISO-8859-1","redirectlocation":"","scraper":{},"duration":66767500,"resultfile":"","url":"https://google.com","host":"CVS/Entries.google.com"},{"input":{"FFUFHASH":"07f07e0","FUZZ":"CVS/Root"},"position":224,"status":200,"length":22900,"words":587,"lines":19,"content-type":"text/html; charset=ISO-8859-1","redirectlocation":"","scraper":{},"duration":64275600,"resultfile":"","url":"https://google.com","host":"CVS/Root.google.com"},{"input":{"FFUFHASH":"07f07f3","FUZZ":"Education"},"position":243,"status":301,"length":220,"words":9,"lines":7,"content-type":"text/html; charset=UTF-8","redirectlocation":"https://edu.google.com/","scraper":{},"duration":33321600,"resultfile":"","url":"https://google.com","host":"Education.google.com"},{"input":{"FFUFHASH":"07f07fd","FUZZ":"Games"},"position":253,"status":301,"length":226,"words":9,"lines":7,"content-type":"text/html; charset=UTF-8","redirectlocation":"https://plus.google.com/games","scraper":{},"duration":34670700,"resultfile":"","url":"https://google.com","host":"Games.google.com"},{"input":{"FFUFHASH":"07f07ef","FUZZ":"Documents and Settings"},"position":239,"status":200,"length":22797,"words":587,"lines":19,"content-type":"text/html; charset=ISO-8859-1","redirectlocation":"","scraper":{},"duration":65018400,"resultfile":"","url":"https://google.com","host":"Documents and Settings.google.com"},{"input":{"FFUFHASH":"07f07103","FUZZ":"Help"},"position":259,"status":301,"length":224,"words":9,"lines":7,"content-type":"text/html; charset=UTF-8","redirectlocation":"https://support.google.com/","scraper":{},"duration":35712100,"resultfile":"","url":"https://google.com","host":"Help.google.com"},{"input":{"FFUFHASH":"07f07102","FUZZ":"Health"},"position":258,"status":302,"length":219,"words":9,"lines":7,"content-type":"text/html; charset=UTF-8","redirectlocation":"https://health.google/","scraper":{},"duration":47973600,"resultfile":"","url":"https://google.com","host":"Health.google.com"},{"input":{"FFUFHASH":"07f07107","FUZZ":"Image"},"position":263,"status":301,"length":223,"words":9,"lines":7,"content-type":"text/html; charset=UTF-8","redirectlocation":"https://images.google.com/","scraper":{},"duration":38215800,"resultfile":"","url":"https://google.com","host":"Image.google.com"},{"input":{"FFUFHASH":"07f07104","FUZZ":"Home"},"position":260,"status":302,"length":0,"words":1,"lines":1,"content-type":"application/binary","redirectlocation":"https://home.google.com/welcome/","scraper":{},"duration":57644700,"resultfile":"","url":"https://google.com","host":"Home.google.com"},{"input":{"FFUFHASH":"07f07108","FUZZ":"Images"},"position":264,"status":200,"length":21712,"words":568,"lines":18,"content-type":"text/html; charset=ISO-8859-1","redirectlocation":"","scraper":{},"duration":79811000,"resultfile":"","url":"https://google.com","host":"Images.google.com"},{"input":{"FFUFHASH":"07f07d9","FUZZ":"Business"},"position":217,"status":302,"length":0,"words":1,"lines":1,"content-type":"application/binary","redirectlocation":"https://support.google.com/business?p=browser_support","scraper":{},"duration":258013700,"resultfile":"","url":"https://google.com","host":"Business.google.com"},{"input":{"FFUFHASH":"07f07119","FUZZ":"M"},"position":281,"status":302,"length":282,"words":9,"lines":7,"content-type":"text/html; charset=UTF-8","redirectlocation":"https://get.google.com/apptips/apps?utm_source=googlemobile\u0026utm_campaign=redirect","scraper":{},"duration":43353400,"resultfile":"","url":"https://google.com","host":"M.google.com"},{"input":{"FFUFHASH":"07f07c4","FUZZ":"ADMIN"},"position":196,"status":302,"length":371,"words":9,"lines":7,"content-type":"text/html; charset=UTF-8","redirectlocation":"https://www.google.com/sorry/index?continue=https://admin.google.com/\u0026q=EgRzSdhbGJXajLcGIjB1LzCKMW5s4F13FTnnIcZ0E-vI7EIetsI3ug3JYYDGxjPDYtjTLxyOstJIZKmuUyQyBj5qY25kcloBQw","scraper":{},"duration":342207900,"resultfile":"","url":"https://google.com","host":"ADMIN.google.com"},{"input":{"FFUFHASH":"07f07123","FUZZ":"Music"},"position":291,"status":301,"length":238,"words":9,"lines":7,"content-type":"text/html; charset=UTF-8","redirectlocation":"https://music.youtube.com/googleplaymusic","scraper":{},"duration":42979300,"resultfile":"","url":"https://google.com","host":"Music.google.com"},{"input":{"FFUFHASH":"07f07125","FUZZ":"News"},"position":293,"status":302,"length":0,"words":1,"lines":1,"content-type":"application/binary","redirectlocation":"https://news.google.com/home?hl=en-US\u0026gl=US\u0026ceid=US:en","scraper":{},"duration":55059300,"resultfile":"","url":"https://google.com","host":"News.google.com"},{"input":{"FFUFHASH":"07f07133","FUZZ":"Privacy"},"position":307,"status":301,"length":219,"words":9,"lines":7,"content-type":"text/html; charset=UTF-8","redirectlocation":"https://safety.google/","scraper":{},"duration":35112900,"resultfile":"","url":"https://google.com","host":"Privacy.google.com"},{"input":{"FFUFHASH":"07f07140","FUZZ":"Research"},"position":320,"status":302,"length":221,"words":9,"lines":7,"content-type":"text/html; charset=UTF-8","redirectlocation":"https://research.google/","scraper":{},"duration":44115600,"resultfile":"","url":"https://google.com","host":"Research.google.com"},{"input":{"FFUFHASH":"07f07135","FUZZ":"Program Files"},"position":309,"status":200,"length":22891,"words":587,"lines":19,"content-type":"text/html; charset=ISO-8859-1","redirectlocation":"","scraper":{},"duration":64757300,"resultfile":"","url":"https://google.com","host":"Program Files.google.com"},{"input":{"FFUFHASH":"07f07149","FUZZ":"Search"},"position":329,"status":301,"length":220,"words":9,"lines":7,"content-type":"text/html; charset=UTF-8","redirectlocation":"https://www.google.com/","scraper":{},"duration":34423800,"resultfile":"","url":"https://google.com","host":"Search.google.com"},{"input":{"FFUFHASH":"07f0714a","FUZZ":"Security"},"position":330,"status":301,"length":234,"words":9,"lines":7,"content-type":"text/html; charset=UTF-8","redirectlocation":"https://myaccount.google.com/security","scraper":{},"duration":34060000,"resultfile":"","url":"https://google.com","host":"Security.google.com"},{"input":{"FFUFHASH":"07f0714d","FUZZ":"Services"},"position":333,"status":301,"length":220,"words":9,"lines":7,"content-type":"text/html; charset=UTF-8","redirectlocation":"https://www.google.com/","scraper":{},"duration":37713500,"resultfile":"","url":"https://google.com","host":"Services.google.com"},{"input":{"FFUFHASH":"07f07c9","FUZZ":"Admin"},"position":201,"status":302,"length":371,"words":9,"lines":7,"content-type":"text/html; charset=UTF-8","redirectlocation":"https://www.google.com/sorry/index?continue=https://admin.google.com/\u0026q=EgRzSdhbGJXajLcGIjB1LzCKMW5s4F13FTnnIcZ0E-vI7EIetsI3ug3JYYDGxjPDYtjTLxyOstJIZKmuUyQyBj5qY25kcloBQw","scraper":{},"duration":506489700,"resultfile":"","url":"https://google.com","host":"Admin.google.com"},{"input":{"FFUFHASH":"07f07150","FUZZ":"Shibboleth.sso/Metadata"},"position":336,"status":200,"length":22855,"words":587,"lines":19,"content-type":"text/html; charset=ISO-8859-1","redirectlocation":"","scraper":{},"duration":78483200,"resultfile":"","url":"https://google.com","host":"Shibboleth.sso/Metadata.google.com"},{"input":{"FFUFHASH":"07f07166","FUZZ":"Travel"},"position":358,"status":301,"length":226,"words":9,"lines":7,"content-type":"text/html; charset=UTF-8","redirectlocation":"https://www.google.com/travel","scraper":{},"duration":33357100,"resultfile":"","url":"https://google.com","host":"Travel.google.com"},{"input":{"FFUFHASH":"07f0716c","FUZZ":"Video"},"position":364,"status":301,"length":227,"words":9,"lines":7,"content-type":"text/html; charset=UTF-8","redirectlocation":"https://www.google.com/videohp","scraper":{},"duration":51172200,"resultfile":"","url":"https://google.com","host":"Video.google.com"},{"input":{"FFUFHASH":"07f07d7","FUZZ":"Books"},"position":215,"status":200,"length":2069152,"words":19608,"lines":4394,"content-type":"text/html; charset=ISO-8859-1","redirectlocation":"","scraper":{},"duration":309879100,"resultfile":"","url":"https://google.com","host":"Books.google.com"},{"input":{"FFUFHASH":"07f07194","FUZZ":"_framework/wasm/dotnet.wasm"},"position":404,"status":200,"length":22903,"words":587,"lines":19,"content-type":"text/html; charset=ISO-8859-1","redirectlocation":"","scraper":{},"duration":80167200,"resultfile":"","url":"https://google.com","host":"_framework/wasm/dotnet.wasm.google.com"},{"input":{"FFUFHASH":"07f07193","FUZZ":"_framework/blazor.webassembly.js"},"position":403,"status":200,"length":22879,"words":587,"lines":19,"content-type":"text/html; charset=ISO-8859-1","redirectlocation":"","scraper":{},"duration":83912200,"resultfile":"","url":"https://google.com","host":"_framework/blazor.webassembly.js.google.com"},{"input":{"FFUFHASH":"07f07195","FUZZ":"_framework/_bin/WebAssembly.Bindings.dll"},"position":405,"status":200,"length":22854,"words":587,"lines":19,"content-type":"text/html; charset=ISO-8859-1","redirectlocation":"","scraper":{},"duration":82427800,"resultfile":"","url":"https://google.com","host":"_framework/_bin/WebAssembly.Bindings.dll.google.com"},{"input":{"FFUFHASH":"07f07192","FUZZ":"_framework/blazor.boot.json"},"position":402,"status":200,"length":22877,"words":587,"lines":19,"content-type":"text/html; charset=ISO-8859-1","redirectlocation":"","scraper":{},"duration":94263400,"resultfile":"","url":"https://google.com","host":"_framework/blazor.boot.json.google.com"},{"input":{"FFUFHASH":"07f0715c","FUZZ":"Support"},"position":348,"status":200,"length":1164525,"words":43003,"lines":4581,"content-type":"text/html; charset=UTF-8","redirectlocation":"","scraper":{},"duration":160437900,"resultfile":"","url":"https://google.com","host":"Support.google.com"},{"input":{"FFUFHASH":"07f071bd","FUZZ":"_vti_bin/_vti_adm/admin.dll"},"position":445,"status":200,"length":22881,"words":587,"lines":19,"content-type":"text/html; charset=ISO-8859-1","redirectlocation":"","scraper":{},"duration":68273500,"resultfile":"","url":"https://google.com","host":"_vti_bin/_vti_adm/admin.dll.google.com"},{"input":{"FFUFHASH":"07f071be","FUZZ":"_vti_bin/_vti_aut/author.dll"},"position":446,"status":200,"length":22875,"words":587,"lines":19,"content-type":"text/html; charset=ISO-8859-1","redirectlocation":"","scraper":{},"duration":81262600,"resultfile":"","url":"https://google.com","host":"_vti_bin/_vti_aut/author.dll.google.com"},{"input":{"FFUFHASH":"07f071bf","FUZZ":"_vti_bin/shtml.dll"},"position":447,"status":200,"length":22871,"words":587,"lines":19,"content-type":"text/html; charset=ISO-8859-1","redirectlocation":"","scraper":{},"duration":86977800,"resultfile":"","url":"https://google.com","host":"_vti_bin/shtml.dll.google.com"},{"input":{"FFUFHASH":"07f071d0","FUZZ":"about"},"position":464,"status":301,"length":218,"words":9,"lines":7,"content-type":"text/html; charset=UTF-8","redirectlocation":"https://about.google/","scraper":{},"duration":34019100,"resultfile":"","url":"https://google.com","host":"about.google.com"},{"input":{"FFUFHASH":"07f071e6","FUZZ":"account"},"position":486,"status":302,"length":226,"words":9,"lines":7,"content-type":"text/html; charset=UTF-8","redirectlocation":"https://myaccount.google.com/","scraper":{},"duration":41799100,"resultfile":"","url":"https://google.com","host":"account.google.com"},{"input":{"FFUFHASH":"07f071eb","FUZZ":"accounts"},"position":491,"status":302,"length":365,"words":14,"lines":11,"content-type":"text/html; charset=UTF-8","redirectlocation":"https://accounts.google.com/ServiceLogin?passive=1209600\u0026continue=https%3A%2F%2Faccounts.google.com%2F\u0026followup=https%3A%2F%2Faccounts.google.com%2F","scraper":{},"duration":41636600,"resultfile":"","url":"https://google.com","host":"accounts.google.com"},{"input":{"FFUFHASH":"07f071f2","FUZZ":"actions"},"position":498,"status":302,"length":235,"words":9,"lines":7,"content-type":"text/html; charset=UTF-8","redirectlocation":"https://developers.google.com/actions/","scraper":{},"duration":43738800,"resultfile":"","url":"https://google.com","host":"actions.google.com"},{"input":{"FFUFHASH":"07f071f9","FUZZ":"activity"},"position":505,"status":302,"length":0,"words":1,"lines":1,"content-type":"application/binary","redirectlocation":"https://myactivity.google.com/","scraper":{},"duration":103245000,"resultfile":"","url":"https://google.com","host":"activity.google.com"},{"input":{"FFUFHASH":"07f07154","FUZZ":"Sites"},"position":340,"status":302,"length":363,"words":14,"lines":11,"content-type":"text/html; charset=UTF-8","redirectlocation":"https://accounts.google.com/ServiceLogin?service=jotspot\u0026passive=1209600\u0026continue=https://sites.google.com/\u0026followup=https://sites.google.com/","scraper":{},"duration":766561900,"resultfile":"","url":"https://google.com","host":"Sites.google.com"},{"input":{"FFUFHASH":"07f0723c","FUZZ":"ads"},"position":572,"status":302,"length":0,"words":1,"lines":1,"content-type":"application/binary","redirectlocation":"https://ads.google.com/intl/en_VN/home/","scraper":{},"duration":93760300,"resultfile":"","url":"https://google.com","host":"ads.google.com"},{"input":{"FFUFHASH":"07f0720d","FUZZ":"admin"},"position":525,"status":302,"length":371,"words":9,"lines":7,"content-type":"text/html; charset=UTF-8","redirectlocation":"https://www.google.com/sorry/index?continue=https://admin.google.com/\u0026q=EgRzSdhbGJbajLcGIjBaQm3SX8jq4OiZ_d1ggqwBKCPiNSJUELJv1sLYMl43IPJgzq4GNCTW8FgYY0bdPZwyBj5qY25kcloBQw","scraper":{},"duration":351799200,"resultfile":"","url":"https://google.com","host":"admin.google.com"},{"input":{"FFUFHASH":"07f07266","FUZZ":"alerts"},"position":614,"status":301,"length":227,"words":9,"lines":7,"content-type":"text/html; charset=UTF-8","redirectlocation":"https://www.google.com/alerts/","scraper":{},"duration":42003600,"resultfile":"","url":"https://google.com","host":"alerts.google.com"},{"input":{"FFUFHASH":"07f0727d","FUZZ":"analytics"},"position":637,"status":301,"length":240,"words":9,"lines":7,"content-type":"text/html; charset=UTF-8","redirectlocation":"https://analytics.google.com/analytics/web/","scraper":{},"duration":42641700,"resultfile":"","url":"https://google.com","host":"analytics.google.com"},{"input":{"FFUFHASH":"07f07280","FUZZ":"android/config"},"position":640,"status":200,"length":22774,"words":587,"lines":19,"content-type":"text/html; charset=ISO-8859-1","redirectlocation":"","scraper":{},"duration":65475100,"resultfile":"","url":"https://google.com","host":"android/config.google.com"},{"input":{"FFUFHASH":"07f0728b","FUZZ":"answers"},"position":651,"status":302,"length":231,"words":9,"lines":7,"content-type":"text/html; charset=UTF-8","redirectlocation":"http://answers.google.com/answers/","scraper":{},"duration":35274900,"resultfile":"","url":"https://google.com","host":"answers.google.com"},{"input":{"FFUFHASH":"07f0728a","FUZZ":"answer"},"position":650,"status":302,"length":220,"words":9,"lines":7,"content-type":"text/html; charset=UTF-8","redirectlocation":"https://www.google.com/","scraper":{},"duration":43020200,"resultfile":"","url":"https://google.com","host":"answer.google.com"},{"input":{"FFUFHASH":"07f0729b","FUZZ":"apis"},"position":667,"status":301,"length":226,"words":9,"lines":7,"content-type":"text/html; charset=UTF-8","redirectlocation":"http://developers.google.com/","scraper":{},"duration":32811400,"resultfile":"","url":"https://google.com","host":"apis.google.com"},{"input":{"FFUFHASH":"07f07291","FUZZ":"aol"},"position":657,"status":200,"length":22914,"words":587,"lines":19,"content-type":"text/html; charset=ISO-8859-1","redirectlocation":"","scraper":{},"duration":67123400,"resultfile":"","url":"https://google.com","host":"aol.google.com"},{"input":{"FFUFHASH":"07f0729a","FUZZ":"api/experiments/configurations"},"position":666,"status":200,"length":22804,"words":587,"lines":19,"content-type":"text/html; charset=ISO-8859-1","redirectlocation":"","scraper":{},"duration":66135400,"resultfile":"","url":"https://google.com","host":"api/experiments/configurations.google.com"},{"input":{"FFUFHASH":"07f07299","FUZZ":"api/experiments"},"position":665,"status":200,"length":22799,"words":587,"lines":19,"content-type":"text/html; charset=ISO-8859-1","redirectlocation":"","scraper":{},"duration":75876200,"resultfile":"","url":"https://google.com","host":"api/experiments.google.com"},{"input":{"FFUFHASH":"07f072b2","FUZZ":"apps"},"position":690,"status":301,"length":223,"words":9,"lines":7,"content-type":"text/html; charset=UTF-8","redirectlocation":"https://gsuite.google.com/","scraper":{},"duration":35952200,"resultfile":"","url":"https://google.com","host":"apps.google.com"},{"input":{"FFUFHASH":"07f072bb","FUZZ":"archive"},"position":699,"status":302,"length":220,"words":9,"lines":7,"content-type":"text/html; charset=UTF-8","redirectlocation":"https://archive.google/","scraper":{},"duration":34386500,"resultfile":"","url":"https://google.com","host":"archive.google.com"},{"input":{"FFUFHASH":"07f072cd","FUZZ":"asia"},"position":717,"status":200,"length":22886,"words":587,"lines":19,"content-type":"text/html; charset=ISO-8859-1","redirectlocation":"","scraper":{},"duration":74607500,"resultfile":"","url":"https://google.com","host":"asia.google.com"},{"input":{"FFUFHASH":"07f0736e","FUZZ":"blog"},"position":878,"status":301,"length":221,"words":9,"lines":7,"content-type":"text/html; charset=UTF-8","redirectlocation":"https://www.blog.google/","scraper":{},"duration":43571000,"resultfile":"","url":"https://google.com","host":"blog.google.com"},{"input":{"FFUFHASH":"07f07374","FUZZ":"blogger"},"position":884,"status":301,"length":227,"words":9,"lines":7,"content-type":"text/html; charset=UTF-8","redirectlocation":"https://www.google.com/blogger","scraper":{},"duration":43991600,"resultfile":"","url":"https://google.com","host":"blogger.google.com"},{"input":{"FFUFHASH":"07f07377","FUZZ":"blogs"},"position":887,"status":302,"length":220,"words":9,"lines":7,"content-type":"text/html; charset=UTF-8","redirectlocation":"https://www.google.com/","scraper":{},"duration":44468300,"resultfile":"","url":"https://google.com","host":"blogs.google.com"},{"input":{"FFUFHASH":"07f0738c","FUZZ":"bookmarks"},"position":908,"status":301,"length":229,"words":9,"lines":7,"content-type":"text/html; charset=UTF-8","redirectlocation":"https://www.google.com/bookmarks","scraper":{},"duration":32557600,"resultfile":"","url":"https://google.com","host":"bookmarks.google.com"},{"input":{"FFUFHASH":"07f073b1","FUZZ":"business"},"position":945,"status":302,"length":0,"words":1,"lines":1,"content-type":"application/binary","redirectlocation":"https://support.google.com/business?p=browser_support","scraper":{},"duration":250861200,"resultfile":"","url":"https://google.com","host":"business.google.com"},{"input":{"FFUFHASH":"07f073e0","FUZZ":"careers"},"position":992,"status":301,"length":0,"words":1,"lines":1,"content-type":"text/html; charset=utf-8","redirectlocation":"https://www.google.com/about/careers/applications/","scraper":{},"duration":268233500,"resultfile":"","url":"https://google.com","host":"careers.google.com"},{"input":{"FFUFHASH":"07f07414","FUZZ":"cgi-bin/"},"position":1044,"status":200,"length":22878,"words":587,"lines":19,"content-type":"text/html; charset=ISO-8859-1","redirectlocation":"","scraper":{},"duration":68428200,"resultfile":"","url":"https://google.com","host":"cgi-bin/.google.com"},{"input":{"FFUFHASH":"07f073c5","FUZZ":"calendar"},"position":965,"status":302,"length":0,"words":1,"lines":1,"content-type":"application/binary","redirectlocation":"https://calendar.google.com/calendar/u/0/r","scraper":{},"duration":456295500,"resultfile":"","url":"https://google.com","host":"calendar.google.com"},{"input":{"FFUFHASH":"07f07446","FUZZ":"chrome"},"position":1094,"status":301,"length":227,"words":9,"lines":7,"content-type":"text/html; charset=UTF-8","redirectlocation":"https://www.google.com/chrome/","scraper":{},"duration":44903100,"resultfile":"","url":"https://google.com","host":"chrome.google.com"},{"input":{"FFUFHASH":"07f07430","FUZZ":"channel"},"position":1072,"status":200,"length":1463559,"words":24863,"lines":301,"content-type":"text/html; charset=utf-8","redirectlocation":"","scraper":{},"duration":82152000,"resultfile":"","url":"https://google.com","host":"channel.google.com"},{"input":{"FFUFHASH":"07f07435","FUZZ":"chat"},"position":1077,"status":302,"length":0,"words":1,"lines":1,"content-type":"application/binary","redirectlocation":"https://accounts.google.com/ServiceLogin?service=dynamite\u0026passive=1209600\u0026osid=1\u0026continue=https://chat.google.com/\u0026emr=1","scraper":{},"duration":312556300,"resultfile":"","url":"https://google.com","host":"chat.google.com"},{"input":{"FFUFHASH":"07f0738d","FUZZ":"books"},"position":909,"status":200,"length":2069152,"words":19608,"lines":4394,"content-type":"text/html; charset=ISO-8859-1","redirectlocation":"","scraper":{},"duration":525266700,"resultfile":"","url":"https://google.com","host":"books.google.com"},{"input":{"FFUFHASH":"07f0747d","FUZZ":"code"},"position":1149,"status":200,"length":5418,"words":1521,"lines":161,"content-type":"text/html","redirectlocation":"","scraper":{},"duration":53155000,"resultfile":"","url":"https://google.com","host":"code.google.com"},{"input":{"FFUFHASH":"07f0743e","FUZZ":"checks"},"position":1086,"status":200,"length":377136,"words":32873,"lines":909,"content-type":"text/html","redirectlocation":"","scraper":{},"duration":53142800,"resultfile":"","url":"https://google.com","host":"checks.google.com"},{"input":{"FFUFHASH":"07f074a8","FUZZ":"compare"},"position":1192,"status":302,"length":220,"words":9,"lines":7,"content-type":"text/html; charset=UTF-8","redirectlocation":"https://www.google.com/","scraper":{},"duration":42899100,"resultfile":"","url":"https://google.com","host":"compare.google.com"},{"input":{"FFUFHASH":"07f074dc","FUZZ":"contacts"},"position":1244,"status":302,"length":0,"words":1,"lines":1,"content-type":"application/binary","redirectlocation":"https://accounts.google.com/ServiceLogin?passive=1209600\u0026continue=https://contacts.google.com/\u0026followup=https://contacts.google.com/","scraper":{},"duration":55923000,"resultfile":"","url":"https://google.com","host":"contacts.google.com"},{"input":{"FFUFHASH":"07f07537","FUZZ":"cse"},"position":1335,"status":301,"length":224,"words":9,"lines":7,"content-type":"text/html; charset=UTF-8","redirectlocation":"https://cse.google.com/cse/","scraper":{},"duration":379305500,"resultfile":"","url":"https://google.com","host":"cse.google.com"},{"input":{"FFUFHASH":"07f075a6","FUZZ":"desktop"},"position":1446,"status":200,"length":283,"words":18,"lines":10,"content-type":"text/html","redirectlocation":"","scraper":{},"duration":35121500,"resultfile":"","url":"https://google.com","host":"desktop.google.com"},{"input":{"FFUFHASH":"07f075b3","FUZZ":"developer"},"position":1459,"status":301,"length":227,"words":9,"lines":7,"content-type":"text/html; charset=UTF-8","redirectlocation":"https://developers.google.com/","scraper":{},"duration":32588800,"resultfile":"","url":"https://google.com","host":"developer.google.com"},{"input":{"FFUFHASH":"07f075a4","FUZZ":"design"},"position":1444,"status":302,"length":0,"words":1,"lines":1,"content-type":"text/html; charset=utf-8","redirectlocation":"https://design.google/","scraper":{},"duration":247043300,"resultfile":"","url":"https://google.com","host":"design.google.com"},{"input":{"FFUFHASH":"07f075eb","FUZZ":"dl"},"position":1515,"status":302,"length":52,"words":2,"lines":3,"content-type":"text/html; charset=utf-8","redirectlocation":"https://www.google.com/chrome","scraper":{},"duration":36407800,"resultfile":"","url":"https://google.com","host":"dl.google.com"},{"input":{"FFUFHASH":"07f07603","FUZZ":"domains"},"position":1539,"status":301,"length":220,"words":9,"lines":7,"content-type":"text/html; charset=UTF-8","redirectlocation":"https://domains.google/","scraper":{},"duration":33061200,"resultfile":"","url":"https://google.com","host":"domains.google.com"},{"input":{"FFUFHASH":"07f07608","FUZZ":"doubleclick"},"position":1544,"status":301,"length":251,"words":9,"lines":7,"content-type":"text/html; charset=UTF-8","redirectlocation":"https://marketingplatform.google.com/about/enterprise/","scraper":{},"duration":33241800,"resultfile":"","url":"https://google.com","host":"doubleclick.google.com"},{"input":{"FFUFHASH":"07f07604","FUZZ":"donate"},"position":1540,"status":302,"length":0,"words":1,"lines":1,"content-type":"application/binary","redirectlocation":"https://donate.google.com/history","scraper":{},"duration":76046100,"resultfile":"","url":"https://google.com","host":"donate.google.com"},{"input":{"FFUFHASH":"07f075f4","FUZZ":"doc"},"position":1524,"status":307,"length":0,"words":1,"lines":1,"content-type":"application/binary","redirectlocation":"https://docs.google.com/","scraper":{},"duration":316355000,"resultfile":"","url":"https://google.com","host":"doc.google.com"},{"input":{"FFUFHASH":"07f075f9","FUZZ":"docs"},"position":1529,"status":302,"length":0,"words":1,"lines":1,"content-type":"application/binary","redirectlocation":"https://accounts.google.com/ServiceLogin?passive=1209600\u0026osid=1\u0026continue=https://docs.google.com/\u0026followup=https://docs.google.com/\u0026emr=1","scraper":{},"duration":303521200,"resultfile":"","url":"https://google.com","host":"docs.google.com"},{"input":{"FFUFHASH":"07f075ff","FUZZ":"documents"},"position":1535,"status":307,"length":0,"words":1,"lines":1,"content-type":"application/binary","redirectlocation":"https://docs.google.com/","scraper":{},"duration":269316300,"resultfile":"","url":"https://google.com","host":"documents.google.com"},{"input":{"FFUFHASH":"07f07631","FUZZ":"ebooks"},"position":1585,"status":301,"length":227,"words":9,"lines":7,"content-type":"text/html; charset=UTF-8","redirectlocation":"http://books.google.com/ebooks","scraper":{},"duration":56043200,"resultfile":"","url":"https://google.com","host":"ebooks.google.com"},{"input":{"FFUFHASH":"07f07647","FUZZ":"education"},"position":1607,"status":301,"length":220,"words":9,"lines":7,"content-type":"text/html; charset=UTF-8","redirectlocation":"https://edu.google.com/","scraper":{},"duration":54207000,"resultfile":"","url":"https://google.com","host":"education.google.com"},{"input":{"FFUFHASH":"07f07674","FUZZ":"encrypted"},"position":1652,"status":301,"length":220,"words":9,"lines":7,"content-type":"text/html; charset=UTF-8","redirectlocation":"https://www.google.com/","scraper":{},"duration":45674900,"resultfile":"","url":"https://google.com","host":"encrypted.google.com"},{"input":{"FFUFHASH":"07f07646","FUZZ":"edu"},"position":1606,"status":200,"length":334222,"words":30396,"lines":2695,"content-type":"text/html","redirectlocation":"","scraper":{},"duration":62062400,"resultfile":"","url":"https://google.com","host":"edu.google.com"},{"input":{"FFUFHASH":"07f075b4","FUZZ":"developers"},"position":1460,"status":200,"length":221279,"words":56911,"lines":9200,"content-type":"text/html; charset=utf-8","redirectlocation":"","scraper":{},"duration":696640500,"resultfile":"","url":"https://google.com","host":"developers.google.com"},{"input":{"FFUFHASH":"07f07680","FUZZ":"enterprise"},"position":1664,"status":301,"length":222,"words":9,"lines":7,"content-type":"text/html; charset=UTF-8","redirectlocation":"https://cloud.google.com/","scraper":{},"duration":41224000,"resultfile":"","url":"https://google.com","host":"enterprise.google.com"},{"input":{"FFUFHASH":"07f076ab","FUZZ":"europe"},"position":1707,"status":200,"length":22941,"words":587,"lines":19,"content-type":"text/html; charset=ISO-8859-1","redirectlocation":"","scraper":{},"duration":63482400,"resultfile":"","url":"https://google.com","host":"europe.google.com"},{"input":{"FFUFHASH":"07f07700","FUZZ":"fi"},"position":1792,"status":302,"length":0,"words":1,"lines":1,"content-type":"application/binary","redirectlocation":"https://fi.google.com/about/","scraper":{},"duration":47172200,"resultfile":"","url":"https://google.com","host":"fi.google.com"},{"input":{"FFUFHASH":"07f076f8","FUZZ":"federation/clients"},"position":1784,"status":200,"length":22846,"words":587,"lines":19,"content-type":"text/html; charset=ISO-8859-1","redirectlocation":"","scraper":{},"duration":67599100,"resultfile":"","url":"https://google.com","host":"federation/clients.google.com"},{"input":{"FFUFHASH":"07f07707","FUZZ":"files"},"position":1799,"status":200,"length":12718,"words":2525,"lines":297,"content-type":"text/html","redirectlocation":"","scraper":{},"duration":45390600,"resultfile":"","url":"https://google.com","host":"files.google.com"},{"input":{"FFUFHASH":"07f0770e","FUZZ":"finance"},"position":1806,"status":302,"length":0,"words":1,"lines":1,"content-type":"application/binary","redirectlocation":"https://www.google.com/finance/","scraper":{},"duration":53115400,"resultfile":"","url":"https://google.com","host":"finance.google.com"},{"input":{"FFUFHASH":"07f07722","FUZZ":"flights"},"position":1826,"status":301,"length":234,"words":9,"lines":7,"content-type":"text/html; charset=UTF-8","redirectlocation":"https://www.google.com/travel/flights","scraper":{},"duration":38016400,"resultfile":"","url":"https://google.com","host":"flights.google.com"},{"input":{"FFUFHASH":"07f07744","FUZZ":"forms"},"position":1860,"status":301,"length":241,"words":9,"lines":7,"content-type":"text/html; charset=UTF-8","redirectlocation":"https://docs.google.com/forms?usp=direct_url","scraper":{},"duration":45427700,"resultfile":"","url":"https://google.com","host":"forms.google.com"},{"input":{"FFUFHASH":"07f07756","FUZZ":"foto"},"position":1878,"status":301,"length":223,"words":9,"lines":7,"content-type":"text/html; charset=UTF-8","redirectlocation":"https://photos.google.com/","scraper":{},"duration":43918000,"resultfile":"","url":"https://google.com","host":"foto.google.com"},{"input":{"FFUFHASH":"07f07757","FUZZ":"fotos"},"position":1879,"status":301,"length":223,"words":9,"lines":7,"content-type":"text/html; charset=UTF-8","redirectlocation":"https://photos.google.com/","scraper":{},"duration":42303900,"resultfile":"","url":"https://google.com","host":"fotos.google.com"},{"input":{"FFUFHASH":"07f07781","FUZZ":"fusion"},"position":1921,"status":302,"length":220,"words":9,"lines":7,"content-type":"text/html; charset=UTF-8","redirectlocation":"https://www.google.com/","scraper":{},"duration":35761300,"resultfile":"","url":"https://google.com","host":"fusion.google.com"},{"input":{"FFUFHASH":"07f07731","FUZZ":"fonts"},"position":1841,"status":200,"length":21944,"words":420,"lines":18,"content-type":"text/html; charset=utf-8","redirectlocation":"","scraper":{},"duration":331929600,"resultfile":"","url":"https://google.com","host":"fonts.google.com"},{"input":{"FFUFHASH":"07f07792","FUZZ":"games"},"position":1938,"status":301,"length":226,"words":9,"lines":7,"content-type":"text/html; charset=UTF-8","redirectlocation":"https://plus.google.com/games","scraper":{},"duration":33456900,"resultfile":"","url":"https://google.com","host":"games.google.com"},{"input":{"FFUFHASH":"07f077aa","FUZZ":"get"},"position":1962,"status":301,"length":220,"words":9,"lines":7,"content-type":"text/html; charset=UTF-8","redirectlocation":"https://www.google.com/","scraper":{},"duration":41900800,"resultfile":"","url":"https://google.com","host":"get.google.com"},{"input":{"FFUFHASH":"07f077fc","FUZZ":"gwt"},"position":2044,"status":301,"length":224,"words":9,"lines":7,"content-type":"text/html; charset=UTF-8","redirectlocation":"https://www.gwtproject.org/","scraper":{},"duration":34447800,"resultfile":"","url":"https://google.com","host":"gwt.google.com"},{"input":{"FFUFHASH":"07f07817","FUZZ":"health"},"position":2071,"status":302,"length":219,"words":9,"lines":7,"content-type":"text/html; charset=UTF-8","redirectlocation":"https://health.google/","scraper":{},"duration":41592200,"resultfile":"","url":"https://google.com","host":"health.google.com"},{"input":{"FFUFHASH":"07f0781c","FUZZ":"help"},"position":2076,"status":301,"length":224,"words":9,"lines":7,"content-type":"text/html; charset=UTF-8","redirectlocation":"https://support.google.com/","scraper":{},"duration":40489800,"resultfile":"","url":"https://google.com","host":"help.google.com"},{"input":{"FFUFHASH":"07f07828","FUZZ":"hire"},"position":2088,"status":200,"length":9003,"words":1025,"lines":133,"content-type":"text/html","redirectlocation":"","scraper":{},"duration":45869000,"resultfile":"","url":"https://google.com","host":"hire.google.com"},{"input":{"FFUFHASH":"07f07831","FUZZ":"home"},"position":2097,"status":302,"length":0,"words":1,"lines":1,"content-type":"application/binary","redirectlocation":"https://home.google.com/welcome/","scraper":{},"duration":48196600,"resultfile":"","url":"https://google.com","host":"home.google.com"},{"input":{"FFUFHASH":"07f0783f","FUZZ":"hotels"},"position":2111,"status":301,"length":233,"words":9,"lines":7,"content-type":"text/html; charset=UTF-8","redirectlocation":"https://www.google.com/travel/hotels","scraper":{},"duration":35402800,"resultfile":"","url":"https://google.com","host":"hotels.google.com"},{"input":{"FFUFHASH":"07f07829","FUZZ":"history"},"position":2089,"status":302,"length":0,"words":1,"lines":1,"content-type":"application/binary","redirectlocation":"https://myactivity.google.com/","scraper":{},"duration":87414300,"resultfile":"","url":"https://google.com","host":"history.google.com"},{"input":{"FFUFHASH":"07f077eb","FUZZ":"groups"},"position":2027,"status":302,"length":0,"words":1,"lines":1,"content-type":"application/binary","redirectlocation":"https://accounts.google.com/ServiceLogin?passive=1209600\u0026osid=1\u0026continue=https://groups.google.com/\u0026followup=https://groups.google.com/","scraper":{},"duration":454439100,"resultfile":"","url":"https://google.com","host":"groups.google.com"},{"input":{"FFUFHASH":"07f0787c","FUZZ":"image"},"position":2172,"status":301,"length":223,"words":9,"lines":7,"content-type":"text/html; charset=UTF-8","redirectlocation":"https://images.google.com/","scraper":{},"duration":38106700,"resultfile":"","url":"https://google.com","host":"image.google.com"},{"input":{"FFUFHASH":"07f07881","FUZZ":"images"},"position":2177,"status":200,"length":21757,"words":568,"lines":18,"content-type":"text/html; charset=ISO-8859-1","redirectlocation":"","scraper":{},"duration":66851100,"resultfile":"","url":"https://google.com","host":"images.google.com"},{"input":{"FFUFHASH":"07f07892","FUZZ":"inbox"},"position":2194,"status":301,"length":230,"words":9,"lines":7,"content-type":"text/html; charset=UTF-8","redirectlocation":"https://mail.google.com/mail/u/0/","scraper":{},"duration":33312000,"resultfile":"","url":"https://google.com","host":"inbox.google.com"},{"input":{"FFUFHASH":"07f078f0","FUZZ":"ios/config"},"position":2288,"status":200,"length":22879,"words":587,"lines":19,"content-type":"text/html; charset=ISO-8859-1","redirectlocation":"","scraper":{},"duration":67801600,"resultfile":"","url":"https://google.com","host":"ios/config.google.com"},{"input":{"FFUFHASH":"07f0792a","FUZZ":"jobs"},"position":2346,"status":301,"length":227,"words":9,"lines":7,"content-type":"text/html; charset=UTF-8","redirectlocation":"https://jobs.google.com/about/","scraper":{},"duration":34421400,"resultfile":"","url":"https://google.com","host":"jobs.google.com"},{"input":{"FFUFHASH":"07f07925","FUZZ":"jigsaw"},"position":2341,"status":200,"length":35880,"words":5978,"lines":606,"content-type":"text/html","redirectlocation":"","scraper":{},"duration":44907400,"resultfile":"","url":"https://google.com","host":"jigsaw.google.com"},{"input":{"FFUFHASH":"07f0796a","FUZZ":"labs"},"position":2410,"status":301,"length":217,"words":9,"lines":7,"content-type":"text/html; charset=UTF-8","redirectlocation":"https://labs.google/","scraper":{},"duration":26901700,"resultfile":"","url":"https://google.com","host":"labs.google.com"},{"input":{"FFUFHASH":"07f0798b","FUZZ":"learning"},"position":2443,"status":302,"length":221,"words":9,"lines":7,"content-type":"text/html; charset=UTF-8","redirectlocation":"https://learning.google/","scraper":{},"duration":34225500,"resultfile":"","url":"https://google.com","host":"learning.google.com"},{"input":{"FFUFHASH":"07f07954","FUZZ":"keep"},"position":2388,"status":302,"length":0,"words":1,"lines":1,"content-type":"application/binary","redirectlocation":"https://accounts.google.com/ServiceLogin?service=memento\u0026passive=1209600\u0026continue=https://keep.google.com/\u0026followup=https://keep.google.com/\u0026ltmpl=keep","scraper":{},"duration":255192200,"resultfile":"","url":"https://google.com","host":"keep.google.com"},{"input":{"FFUFHASH":"07f079ca","FUZZ":"local"},"position":2506,"status":302,"length":221,"words":9,"lines":7,"content-type":"text/html; charset=UTF-8","redirectlocation":"https://maps.google.com/","scraper":{},"duration":34623900,"resultfile":"","url":"https://google.com","host":"local.google.com"},{"input":{"FFUFHASH":"07f079fd","FUZZ":"m"},"position":2557,"status":302,"length":282,"words":9,"lines":7,"content-type":"text/html; charset=UTF-8","redirectlocation":"https://get.google.com/apptips/apps?utm_source=googlemobile\u0026utm_campaign=redirect","scraper":{},"duration":42871400,"resultfile":"","url":"https://google.com","host":"m.google.com"},{"input":{"FFUFHASH":"07f07902","FUZZ":"isp"},"position":2306,"status":302,"length":0,"words":1,"lines":1,"content-type":"text/html; charset=utf-8","redirectlocation":"https://accounts.google.com/ServiceLogin?service=ah\u0026passive=true\u0026continue=https://isp.google.com/","scraper":{},"duration":1157554100,"resultfile":"","url":"https://google.com","host":"isp.google.com"},{"input":{"FFUFHASH":"07f07a37","FUZZ":"manufacturers"},"position":2615,"status":302,"length":233,"words":9,"lines":7,"content-type":"text/html; charset=UTF-8","redirectlocation":"https://manufacturers.google.com/mc/","scraper":{},"duration":44614500,"resultfile":"","url":"https://google.com","host":"manufacturers.google.com"},{"input":{"FFUFHASH":"07f07a38","FUZZ":"map"},"position":2616,"status":301,"length":221,"words":9,"lines":7,"content-type":"text/html; charset=UTF-8","redirectlocation":"https://maps.google.com/","scraper":{},"duration":35197900,"resultfile":"","url":"https://google.com","host":"map.google.com"},{"input":{"FFUFHASH":"07f07a11","FUZZ":"mail"},"position":2577,"status":301,"length":215,"words":14,"lines":11,"content-type":"text/html; charset=UTF-8","redirectlocation":"/mail/","scraper":{},"duration":193841500,"resultfile":"","url":"https://google.com","host":"mail.google.com"},{"input":{"FFUFHASH":"07f07a39","FUZZ":"maps"},"position":2617,"status":302,"length":225,"words":9,"lines":7,"content-type":"text/html; charset=UTF-8","redirectlocation":"https://maps.google.com/maps","scraper":{},"duration":49496300,"resultfile":"","url":"https://google.com","host":"maps.google.com"},{"input":{"FFUFHASH":"07f07a49","FUZZ":"maven"},"position":2633,"status":301,"length":236,"words":9,"lines":7,"content-type":"text/html; charset=UTF-8","redirectlocation":"https://maven.google.com/web/index.html","scraper":{},"duration":34909900,"resultfile":"","url":"https://google.com","host":"maven.google.com"},{"input":{"FFUFHASH":"07f07a70","FUZZ":"messages"},"position":2672,"status":200,"length":1805,"words":239,"lines":32,"content-type":"text/html","redirectlocation":"","scraper":{},"duration":29189800,"resultfile":"","url":"https://google.com","host":"messages.google.com"},{"input":{"FFUFHASH":"07f07a7a","FUZZ":"mfa/challenge"},"position":2682,"status":200,"length":22852,"words":587,"lines":19,"content-type":"text/html; charset=ISO-8859-1","redirectlocation":"","scraper":{},"duration":66427800,"resultfile":"","url":"https://google.com","host":"mfa/challenge.google.com"},{"input":{"FFUFHASH":"07f07a9e","FUZZ":"mobile"},"position":2718,"status":301,"length":227,"words":9,"lines":7,"content-type":"text/html; charset=UTF-8","redirectlocation":"https://www.google.com/mobile/","scraper":{},"duration":35437700,"resultfile":"","url":"https://google.com","host":"mobile.google.com"},{"input":{"FFUFHASH":"07f07abf","FUZZ":"movies"},"position":2751,"status":301,"length":223,"words":9,"lines":7,"content-type":"text/html; charset=UTF-8","redirectlocation":"https://youtube.com/movies","scraper":{},"duration":32732700,"resultfile":"","url":"https://google.com","host":"movies.google.com"},{"input":{"FFUFHASH":"07f07adb","FUZZ":"music"},"position":2779,"status":301,"length":238,"words":9,"lines":7,"content-type":"text/html; charset=UTF-8","redirectlocation":"https://music.youtube.com/googleplaymusic","scraper":{},"duration":34746000,"resultfile":"","url":"https://google.com","host":"music.google.com"},{"input":{"FFUFHASH":"07f07ae3","FUZZ":"myaccount"},"position":2787,"status":302,"length":0,"words":1,"lines":1,"content-type":"application/binary","redirectlocation":"https://myaccount.google.com/intro","scraper":{},"duration":48225500,"resultfile":"","url":"https://google.com","host":"myaccount.google.com"},{"input":{"FFUFHASH":"07f07b0f","FUZZ":"news"},"position":2831,"status":302,"length":0,"words":1,"lines":1,"content-type":"application/binary","redirectlocation":"https://news.google.com/home?hl=en-US\u0026gl=US\u0026ceid=US:en","scraper":{},"duration":46891900,"resultfile":"","url":"https://google.com","host":"news.google.com"},{"input":{"FFUFHASH":"07f07b2f","FUZZ":"notifications"},"position":2863,"status":302,"length":0,"words":1,"lines":1,"content-type":"application/binary","redirectlocation":"https://www.google.com","scraper":{},"duration":61221100,"resultfile":"","url":"https://google.com","host":"notifications.google.com"},{"input":{"FFUFHASH":"07f07b43","FUZZ":"oauth/device/code"},"position":2883,"status":200,"length":22848,"words":587,"lines":19,"content-type":"text/html; charset=ISO-8859-1","redirectlocation":"","scraper":{},"duration":63071500,"resultfile":"","url":"https://google.com","host":"oauth/device/code.google.com"},{"input":{"FFUFHASH":"07f07b42","FUZZ":"oauth/authorize"},"position":2882,"status":200,"length":22906,"words":587,"lines":19,"content-type":"text/html; charset=ISO-8859-1","redirectlocation":"","scraper":{},"duration":76845300,"resultfile":"","url":"https://google.com","host":"oauth/authorize.google.com"},{"input":{"FFUFHASH":"07f07b45","FUZZ":"oauth/token"},"position":2885,"status":200,"length":22807,"words":587,"lines":19,"content-type":"text/html; charset=ISO-8859-1","redirectlocation":"","scraper":{},"duration":74144600,"resultfile":"","url":"https://google.com","host":"oauth/token.google.com"},{"input":{"FFUFHASH":"07f07b55","FUZZ":"offers"},"position":2901,"status":301,"length":227,"words":9,"lines":7,"content-type":"text/html; charset=UTF-8","redirectlocation":"https://www.google.com/offers/","scraper":{},"duration":37585900,"resultfile":"","url":"https://google.com","host":"offers.google.com"},{"input":{"FFUFHASH":"07f07b44","FUZZ":"oauth/revoke"},"position":2884,"status":200,"length":22851,"words":587,"lines":19,"content-type":"text/html; charset=ISO-8859-1","redirectlocation":"","scraper":{},"duration":74001500,"resultfile":"","url":"https://google.com","host":"oauth/revoke.google.com"},{"input":{"FFUFHASH":"07f07b46","FUZZ":"oauth/token/info"},"position":2886,"status":200,"length":22859,"words":587,"lines":19,"content-type":"text/html; charset=ISO-8859-1","redirectlocation":"","scraper":{},"duration":79441500,"resultfile":"","url":"https://google.com","host":"oauth/token/info.google.com"},{"input":{"FFUFHASH":"07f07b61","FUZZ":"on"},"position":2913,"status":302,"length":223,"words":9,"lines":7,"content-type":"text/html; charset=UTF-8","redirectlocation":"https://on.google.com/hub/","scraper":{},"duration":25618300,"resultfile":"","url":"https://google.com","host":"on.google.com"},{"input":{"FFUFHASH":"07f07b5a","FUZZ":"oidc/register"},"position":2906,"status":200,"length":22963,"words":587,"lines":19,"content-type":"text/html; charset=ISO-8859-1","redirectlocation":"","scraper":{},"duration":76244800,"resultfile":"","url":"https://google.com","host":"oidc/register.google.com"},{"input":{"FFUFHASH":"07f07b71","FUZZ":"opensource"},"position":2929,"status":301,"length":223,"words":9,"lines":7,"content-type":"text/html; charset=UTF-8","redirectlocation":"https://opensource.google/","scraper":{},"duration":35007900,"resultfile":"","url":"https://google.com","host":"opensource.google.com"},{"input":{"FFUFHASH":"07f07bd0","FUZZ":"partners"},"position":3024,"status":301,"length":229,"words":9,"lines":7,"content-type":"text/html; charset=UTF-8","redirectlocation":"https://www.google.com/partners/","scraper":{},"duration":36409900,"resultfile":"","url":"https://google.com","host":"partners.google.com"},{"input":{"FFUFHASH":"07f07bdb","FUZZ":"passwords"},"position":3035,"status":302,"length":0,"words":1,"lines":1,"content-type":"application/binary","redirectlocation":"https://passwords.google.com/intro","scraper":{},"duration":42090900,"resultfile":"","url":"https://google.com","host":"passwords.google.com"},{"input":{"FFUFHASH":"07f07c0e","FUZZ":"photo"},"position":3086,"status":301,"length":223,"words":9,"lines":7,"content-type":"text/html; charset=UTF-8","redirectlocation":"https://photos.google.com/","scraper":{},"duration":35420600,"resultfile":"","url":"https://google.com","host":"photo.google.com"},{"input":{"FFUFHASH":"07f07bdf","FUZZ":"patents"},"position":3039,"status":200,"length":3930,"words":766,"lines":96,"content-type":"text/html","redirectlocation":"","scraper":{},"duration":336028900,"resultfile":"","url":"https://google.com","host":"patents.google.com"},{"input":{"FFUFHASH":"07f07c12","FUZZ":"photos"},"position":3090,"status":302,"length":0,"words":1,"lines":1,"content-type":"application/binary","redirectlocation":"https://www.google.com/photos/about/","scraper":{},"duration":222249800,"resultfile":"","url":"https://google.com","host":"photos.google.com"},{"input":{"FFUFHASH":"07f07c48","FUZZ":"pixel"},"position":3144,"status":302,"length":237,"words":9,"lines":7,"content-type":"text/html; charset=UTF-8","redirectlocation":"https://store.google.com/category/phones","scraper":{},"duration":42431100,"resultfile":"","url":"https://google.com","host":"pixel.google.com"},{"input":{"FFUFHASH":"07f07c4f","FUZZ":"places"},"position":3151,"status":301,"length":411,"words":9,"lines":7,"content-type":"text/html; charset=UTF-8","redirectlocation":"https://www.google.com/business/?gmbsrc=us-en-et-gs-z-gmb-l-z-h~pl|redirect|u\u0026ppsrc=GMBLR\u0026utm_campaign=us-en-et-gs-z-gmb-l-z-h~pl|redirect|u\u0026utm_source=gmb\u0026utm_medium=et\u0026dialog=places-transition","scraper":{},"duration":44652900,"resultfile":"","url":"https://google.com","host":"places.google.com"},{"input":{"FFUFHASH":"07f07c53","FUZZ":"play"},"position":3155,"status":302,"length":0,"words":1,"lines":1,"content-type":"application/binary","redirectlocation":"https://play.google.com/store","scraper":{},"duration":50236200,"resultfile":"","url":"https://google.com","host":"play.google.com"},{"input":{"FFUFHASH":"07f07c5f","FUZZ":"plus"},"position":3167,"status":301,"length":314,"words":9,"lines":7,"content-type":"text/html; charset=UTF-8","redirectlocation":"https://workspaceupdates.googleblog.com/2023/04/new-community-features-for-google-chat-and-an-update-currents%20.html","scraper":{},"duration":42094400,"resultfile":"","url":"https://google.com","host":"plus.google.com"},{"input":{"FFUFHASH":"07f07c69","FUZZ":"podcast"},"position":3177,"status":301,"length":225,"words":9,"lines":7,"content-type":"text/html; charset=UTF-8","redirectlocation":"https://podcasts.google.com/","scraper":{},"duration":34881900,"resultfile":"","url":"https://google.com","host":"podcast.google.com"},{"input":{"FFUFHASH":"07f07c6f","FUZZ":"policies"},"position":3183,"status":200,"length":171476,"words":4170,"lines":288,"content-type":"text/html; charset=utf-8","redirectlocation":"","scraper":{},"duration":59727100,"resultfile":"","url":"https://google.com","host":"policies.google.com"},{"input":{"FFUFHASH":"07f07c9b","FUZZ":"posts"},"position":3227,"status":302,"length":220,"words":9,"lines":7,"content-type":"text/html; charset=UTF-8","redirectlocation":"https://www.google.com/","scraper":{},"duration":35857800,"resultfile":"","url":"https://google.com","host":"posts.google.com"},{"input":{"FFUFHASH":"07f07c6b","FUZZ":"podcasts"},"position":3179,"status":200,"length":531494,"words":22040,"lines":298,"content-type":"text/html; charset=utf-8","redirectlocation":"","scraper":{},"duration":126181300,"resultfile":"","url":"https://google.com","host":"podcasts.google.com"},{"input":{"FFUFHASH":"07f07cbc","FUZZ":"print"},"position":3260,"status":301,"length":222,"words":9,"lines":7,"content-type":"text/html; charset=UTF-8","redirectlocation":"https://books.google.com/","scraper":{},"duration":26236900,"resultfile":"","url":"https://google.com","host":"print.google.com"},{"input":{"FFUFHASH":"07f07cc8","FUZZ":"privacy"},"position":3272,"status":301,"length":219,"words":9,"lines":7,"content-type":"text/html; charset=UTF-8","redirectlocation":"https://safety.google/","scraper":{},"duration":41596600,"resultfile":"","url":"https://google.com","host":"privacy.google.com"},{"input":{"FFUFHASH":"07f07cf7","FUZZ":"profile"},"position":3319,"status":200,"length":1463558,"words":24863,"lines":301,"content-type":"text/html; charset=utf-8","redirectlocation":"","scraper":{},"duration":78756200,"resultfile":"","url":"https://google.com","host":"profile.google.com"},{"input":{"FFUFHASH":"07f07be4","FUZZ":"payments"},"position":3044,"status":302,"length":0,"words":1,"lines":1,"content-type":"application/binary","redirectlocation":"https://payments.google.com/payments/home","scraper":{},"duration":1308777800,"resultfile":"","url":"https://google.com","host":"payments.google.com"},{"input":{"FFUFHASH":"07f07be1","FUZZ":"pay"},"position":3041,"status":302,"length":0,"words":1,"lines":1,"content-type":"application/binary","redirectlocation":"https://wallet.google.com/wallet?p=pgc\u0026utm_source=pgc\u0026utm_medium=website\u0026utm_campaign=redirect","scraper":{},"duration":1353141000,"resultfile":"","url":"https://google.com","host":"pay.google.com"},{"input":{"FFUFHASH":"07f07d73","FUZZ":"reader"},"position":3443,"status":301,"length":233,"words":9,"lines":7,"content-type":"text/html; charset=UTF-8","redirectlocation":"https://www.google.com/reader/about/","scraper":{},"duration":32643500,"resultfile":"","url":"https://google.com","host":"reader.google.com"},{"input":{"FFUFHASH":"07f07db6","FUZZ":"render?url=https://www.google.com"},"position":3510,"status":200,"length":22845,"words":587,"lines":19,"content-type":"text/html; charset=ISO-8859-1","redirectlocation":"","scraper":{},"duration":66542100,"resultfile":"","url":"https://google.com","host":"render?url=https://www.google.com.google.com"},{"input":{"FFUFHASH":"07f07db7","FUZZ":"render/https://www.google.com"},"position":3511,"status":200,"length":22867,"words":587,"lines":19,"content-type":"text/html; charset=ISO-8859-1","redirectlocation":"","scraper":{},"duration":76092000,"resultfile":"","url":"https://google.com","host":"render/https://www.google.com.google.com"},{"input":{"FFUFHASH":"07f07dc7","FUZZ":"reports list"},"position":3527,"status":200,"length":22865,"words":587,"lines":19,"content-type":"text/html; charset=ISO-8859-1","redirectlocation":"","scraper":{},"duration":66658200,"resultfile":"","url":"https://google.com","host":"reports list.google.com"},{"input":{"FFUFHASH":"07f07dd6","FUZZ":"research"},"position":3542,"status":302,"length":221,"words":9,"lines":7,"content-type":"text/html; charset=UTF-8","redirectlocation":"https://research.google/","scraper":{},"duration":34665900,"resultfile":"","url":"https://google.com","host":"research.google.com"},{"input":{"FFUFHASH":"07f07e25","FUZZ":"safety"},"position":3621,"status":302,"length":219,"words":9,"lines":7,"content-type":"text/html; charset=UTF-8","redirectlocation":"https://safety.google/","scraper":{},"duration":36001700,"resultfile":"","url":"https://google.com","host":"safety.google.com"},{"input":{"FFUFHASH":"07f07e34","FUZZ":"sb"},"position":3636,"status":302,"length":220,"words":9,"lines":7,"content-type":"text/html; charset=UTF-8","redirectlocation":"https://www.google.com/","scraper":{},"duration":43343400,"resultfile":"","url":"https://google.com","host":"sb.google.com"},{"input":{"FFUFHASH":"07f07e56","FUZZ":"search"},"position":3670,"status":301,"length":220,"words":9,"lines":7,"content-type":"text/html; charset=UTF-8","redirectlocation":"https://www.google.com/","scraper":{},"duration":43521500,"resultfile":"","url":"https://google.com","host":"search.google.com"},{"input":{"FFUFHASH":"07f07e6c","FUZZ":"security"},"position":3692,"status":301,"length":234,"words":9,"lines":7,"content-type":"text/html; charset=UTF-8","redirectlocation":"https://myaccount.google.com/security","scraper":{},"duration":42262500,"resultfile":"","url":"https://google.com","host":"security.google.com"},{"input":{"FFUFHASH":"07f07e4c","FUZZ":"script"},"position":3660,"status":302,"length":248,"words":14,"lines":11,"content-type":"text/html; charset=UTF-8","redirectlocation":"https://script.google.com/home?authuser","scraper":{},"duration":262422000,"resultfile":"","url":"https://google.com","host":"script.google.com"},{"input":{"FFUFHASH":"07f07d87","FUZZ":"recorder"},"position":3463,"status":302,"length":0,"words":1,"lines":1,"content-type":"application/binary","redirectlocation":"https://recorder.google.com/about","scraper":{},"duration":980554200,"resultfile":"","url":"https://google.com","host":"recorder.google.com"},{"input":{"FFUFHASH":"07f07e94","FUZZ":"services"},"position":3732,"status":301,"length":220,"words":9,"lines":7,"content-type":"text/html; charset=UTF-8","redirectlocation":"https://www.google.com/","scraper":{},"duration":36193200,"resultfile":"","url":"https://google.com","host":"services.google.com"},{"input":{"FFUFHASH":"07f07e99","FUZZ":"servlet/GetProductVersion"},"position":3737,"status":200,"length":22888,"words":587,"lines":19,"content-type":"text/html; charset=ISO-8859-1","redirectlocation":"","scraper":{},"duration":76789100,"resultfile":"","url":"https://google.com","host":"servlet/GetProductVersion.google.com"},{"input":{"FFUFHASH":"07f07f09","FUZZ":"slides"},"position":3849,"status":301,"length":248,"words":9,"lines":7,"content-type":"text/html; charset=UTF-8","redirectlocation":"https://docs.google.com/presentation?usp=direct_url","scraper":{},"duration":26626800,"resultfile":"","url":"https://google.com","host":"slides.google.com"},{"input":{"FFUFHASH":"07f07ebd","FUZZ":"shopping"},"position":3773,"status":200,"length":795065,"words":19203,"lines":149,"content-type":"text/html; charset=utf-8","redirectlocation":"","scraper":{},"duration":134392200,"resultfile":"","url":"https://google.com","host":"shopping.google.com"},{"input":{"FFUFHASH":"07f07efc","FUZZ":"sites"},"position":3836,"status":302,"length":363,"words":14,"lines":11,"content-type":"text/html; charset=UTF-8","redirectlocation":"https://accounts.google.com/ServiceLogin?service=jotspot\u0026passive=1209600\u0026continue=https://sites.google.com/\u0026followup=https://sites.google.com/","scraper":{},"duration":266766000,"resultfile":"","url":"https://google.com","host":"sites.google.com"},{"input":{"FFUFHASH":"07f07f75","FUZZ":"standards"},"position":3957,"status":301,"length":222,"words":9,"lines":7,"content-type":"text/html; charset=UTF-8","redirectlocation":"https://standards.google/","scraper":{},"duration":40724700,"resultfile":"","url":"https://google.com","host":"standards.google.com"},{"input":{"FFUFHASH":"07f07f8d","FUZZ":"store"},"position":3981,"status":302,"length":0,"words":1,"lines":1,"content-type":"application/binary","redirectlocation":"https://store.google.com/regionpicker","scraper":{},"duration":58878900,"resultfile":"","url":"https://google.com","host":"store.google.com"},{"input":{"FFUFHASH":"07f07fc6","FUZZ":"survey"},"position":4038,"status":301,"length":224,"words":9,"lines":7,"content-type":"text/html; charset=UTF-8","redirectlocation":"https://surveys.google.com/","scraper":{},"duration":36720400,"resultfile":"","url":"https://google.com","host":"survey.google.com"},{"input":{"FFUFHASH":"07f07fc7","FUZZ":"surveys"},"position":4039,"status":302,"length":0,"words":1,"lines":1,"content-type":"text/html; charset=utf-8","redirectlocation":"https://surveys.google.com/your-surveys?category=example","scraper":{},"duration":260172300,"resultfile":"","url":"https://google.com","host":"surveys.google.com"},{"input":{"FFUFHASH":"07f07fc2","FUZZ":"support"},"position":4034,"status":200,"length":1164534,"words":43003,"lines":4581,"content-type":"text/html; charset=UTF-8","redirectlocation":"","scraper":{},"duration":166113700,"resultfile":"","url":"https://google.com","host":"support.google.com"},{"input":{"FFUFHASH":"07f07104e","FUZZ":"time"},"position":4174,"status":302,"length":220,"words":9,"lines":7,"content-type":"text/html; charset=UTF-8","redirectlocation":"https://www.google.com/","scraper":{},"duration":33171900,"resultfile":"","url":"https://google.com","host":"time.google.com"},{"input":{"FFUFHASH":"07f07104f","FUZZ":"timeline"},"position":4175,"status":302,"length":422,"words":9,"lines":7,"content-type":"text/html; charset=UTF-8","redirectlocation":"https://accounts.google.com/ServiceLogin?continue=https://timeline.google.com/maps/timeline\u0026rart=ANgoxccxaWLknvJ9Ropl_mSZ0miXdrwX5Q4eYQ59ns-jXtVHRFGe65Leb7XU_UqExXS1QWou40jlLSXlxrFzPoxYD3wOcppc6w\u0026osid=1\u0026authuser=0","scraper":{},"duration":70205200,"resultfile":"","url":"https://google.com","host":"timeline.google.com"},{"input":{"FFUFHASH":"07f071069","FUZZ":"toolbar"},"position":4201,"status":302,"length":240,"words":9,"lines":7,"content-type":"text/html; charset=UTF-8","redirectlocation":"http://www.google.com/toolbar/ie/index.html","scraper":{},"duration":26162800,"resultfile":"","url":"https://google.com","host":"toolbar.google.com"},{"input":{"FFUFHASH":"07f07106b","FUZZ":"tools"},"position":4203,"status":302,"length":226,"words":9,"lines":7,"content-type":"text/html; charset=UTF-8","redirectlocation":"https://www.google.com/chrome","scraper":{},"duration":34166500,"resultfile":"","url":"https://google.com","host":"tools.google.com"},{"input":{"FFUFHASH":"07f071065","FUZZ":"token/revoke"},"position":4197,"status":200,"length":22867,"words":587,"lines":19,"content-type":"text/html; charset=ISO-8859-1","redirectlocation":"","scraper":{},"duration":72328700,"resultfile":"","url":"https://google.com","host":"token/revoke.google.com"},{"input":{"FFUFHASH":"07f071064","FUZZ":"token/introspect"},"position":4196,"status":200,"length":22892,"words":587,"lines":19,"content-type":"text/html; charset=ISO-8859-1","redirectlocation":"","scraper":{},"duration":69984700,"resultfile":"","url":"https://google.com","host":"token/introspect.google.com"},{"input":{"FFUFHASH":"07f07109c","FUZZ":"travel"},"position":4252,"status":301,"length":226,"words":9,"lines":7,"content-type":"text/html; charset=UTF-8","redirectlocation":"https://www.google.com/travel","scraper":{},"duration":40835100,"resultfile":"","url":"https://google.com","host":"travel.google.com"},{"input":{"FFUFHASH":"07f0710a0","FUZZ":"trends"},"position":4256,"status":301,"length":230,"words":9,"lines":7,"content-type":"text/html; charset=UTF-8","redirectlocation":"https://trends.google.com/trends/","scraper":{},"duration":34275800,"resultfile":"","url":"https://google.com","host":"trends.google.com"},{"input":{"FFUFHASH":"07f0710ac","FUZZ":"tv"},"position":4268,"status":302,"length":215,"words":9,"lines":7,"content-type":"text/html; charset=UTF-8","redirectlocation":"https://tv.google/","scraper":{},"duration":36092600,"resultfile":"","url":"https://google.com","host":"tv.google.com"},{"input":{"FFUFHASH":"07f071096","FUZZ":"translate"},"position":4246,"status":200,"length":2533666,"words":94655,"lines":298,"content-type":"text/html; charset=utf-8","redirectlocation":"","scraper":{},"duration":65949300,"resultfile":"","url":"https://google.com","host":"translate.google.com"},{"input":{"FFUFHASH":"07f071113","FUZZ":"v1/client_configs"},"position":4371,"status":200,"length":22838,"words":587,"lines":19,"content-type":"text/html; charset=ISO-8859-1","redirectlocation":"","scraper":{},"duration":63486100,"resultfile":"","url":"https://google.com","host":"v1/client_configs.google.com"},{"input":{"FFUFHASH":"07f071115","FUZZ":"v2/client_configs"},"position":4373,"status":200,"length":22865,"words":587,"lines":19,"content-type":"text/html; charset=ISO-8859-1","redirectlocation":"","scraper":{},"duration":64284500,"resultfile":"","url":"https://google.com","host":"v2/client_configs.google.com"},{"input":{"FFUFHASH":"07f07113a","FUZZ":"video"},"position":4410,"status":301,"length":227,"words":9,"lines":7,"content-type":"text/html; charset=UTF-8","redirectlocation":"https://www.google.com/videohp","scraper":{},"duration":44187100,"resultfile":"","url":"https://google.com","host":"video.google.com"},{"input":{"FFUFHASH":"07f07ffd","FUZZ":"tasks"},"position":4093,"status":302,"length":0,"words":1,"lines":1,"content-type":"application/binary","redirectlocation":"https://accounts.google.com/ServiceLogin?passive=1209600\u0026continue=https://tasks.google.com/\u0026followup=https://tasks.google.com/","scraper":{},"duration":1570953600,"resultfile":"","url":"https://google.com","host":"tasks.google.com"},{"input":{"FFUFHASH":"07f0711a1","FUZZ":"webmaster"},"position":4513,"status":301,"length":231,"words":9,"lines":7,"content-type":"text/html; charset=UTF-8","redirectlocation":"https://www.google.com/webmasters/","scraper":{},"duration":35188700,"resultfile":"","url":"https://google.com","host":"webmaster.google.com"},{"input":{"FFUFHASH":"07f0711a2","FUZZ":"webmasters"},"position":4514,"status":301,"length":231,"words":9,"lines":7,"content-type":"text/html; charset=UTF-8","redirectlocation":"https://www.google.com/webmasters/","scraper":{},"duration":36656200,"resultfile":"","url":"https://google.com","host":"webmasters.google.com"}],"config":{"autocalibration":false,"autocalibration_keyword":"FUZZ","autocalibration_perhost":false,"autocalibration_strategies":["basic"],"autocalibration_strings":[],"colors":false,"cmdline":"C:\\Users\\minhl\\AppData\\Local\\Temp\\go-build1754508248\\b001\\exe\\recon.exe google.com","configfile":"","postdata":"","debuglog":"","delay":{"value":"0.00"},"dirsearch_compatibility":false,"encoders":[],"extensions":[],"fmode":"or","follow_redirects":false,"headers":{"Host":"FUZZ.google.com"},"ignorebody":false,"ignore_wordlist_comments":false,"inputmode":"clusterbomb","cmd_inputnum":100,"inputproviders":[{"name":"wordlist","keyword":"FUZZ","value":"C:\\Users\\minhl\\recon\\src\\data\\input\\common.txt","encoders":"","template":""}],"inputshell":"","json":false,"matchers":{"IsCalibrated":false,"Mutex":{},"Matchers":{"status":{"value":"200-299,301,302,307,401,403,405,500"}},"Filters":{"size":{"value":"1561"}},"PerDomainFilters":{}},"mmode":"or","maxtime":0,"maxtime_job":0,"method":"GET","noninteractive":false,"outputdirectory":"","outputfile":"C:/Users/minhl/recon/src/data/output/FuffDomainHttp.json","outputformat":"json","OutputSkipEmptyFile":false,"proxyurl":"","quiet":false,"rate":0,"raw":false,"recursion":false,"recursion_depth":0,"recursion_strategy":"default","replayproxyurl":"","requestfile":"","requestproto":"https","scraperfile":"","scrapers":"all","sni":"","stop_403":false,"stop_all":false,"stop_errors":false,"threads":40,"timeout":10,"url":"https://google.com","verbose":false,"wordlists":["C:\\Users\\minhl\\recon\\src\\data\\input\\common.txt"],"http2":false,"client-cert":"","client-key":""}}